denseweight/__init__.py
denseweight/denseweight.py
denseweight/utils.py
denseweight-0.1.2.dist-info/LICENSE
denseweight-0.1.2.dist-info/METADATA
denseweight-0.1.2.dist-info/WHEEL
denseweight-0.1.2.dist-info/top_level.txt
denseweight-0.1.2.dist-info/RECORD
