Metadata-Version: 2.1
Name: denseweight
Version: 0.1.2
Summary: The imbalanced regression method DenseWeight
Home-page: https://github.com/steimi/denseweight
Author: Michael Steininger
Author-email: steininger@informatik.uni-wuerzburg.de
License: UNKNOWN
Project-URL: Bug Tracker, https://github.com/steimi/denseweight/issues
Platform: UNKNOWN
Classifier: Programming Language :: Python :: 3
Classifier: License :: OSI Approved :: MIT License
Classifier: Operating System :: OS Independent
Requires-Python: >=3.6
License-File: LICENSE
Requires-Dist: numpy (>=1.20.0)
Requires-Dist: KDEpy
Requires-Dist: scikit-learn
